{
  "timestamp": "2025-06-18T10:23:45.955087",
  "channels": [
    {
      "url": "https://t.me/s/prrofile_purple",
      "enabled": true,
      "metrics": {
        "total_configs": 128,
        "valid_configs": 27,
        "unique_configs": 26,
        "avg_response_time": 0.56,
        "success_count": 1,
        "fail_count": 0,
        "overall_score": 78.51,
        "last_success": "2025-06-18T10:23:44.817448"
      }
    },
    {
      "url": "https://t.me/s/v2ray_free_conf",
      "enabled": true,
      "metrics": {
        "total_configs": 20,
        "valid_configs": 17,
        "unique_configs": 17,
        "avg_response_time": 0.33,
        "success_count": 1,
        "fail_count": 0,
        "overall_score": 95.75,
        "last_success": "2025-06-18T10:23:45.191408"
      }
    },
    {
      "url": "https://t.me/s/PrivateVPNs",
      "enabled": true,
      "metrics": {
        "total_configs": 18,
        "valid_configs": 7,
        "unique_configs": 7,
        "avg_response_time": 0.34,
        "success_count": 1,
        "fail_count": 0,
        "overall_score": 84.22,
        "last_success": "2025-06-18T10:23:45.563241"
      }
    },
    {
      "url": "https://t.me/s/freewireguard",
      "enabled": true,
      "metrics": {
        "total_configs": 10,
        "valid_configs": 10,
        "unique_configs": 10,
        "avg_response_time": 0.36,
        "success_count": 1,
        "fail_count": 0,
        "overall_score": 99.46,
        "last_success": "2025-06-18T10:23:45.953277"
      }
    }
  ]
}