{
  "timestamp": "2025-04-30T12:41:16.028264",
  "channels": [
    {
      "url": "https://t.me/s/prrofile_purple",
      "enabled": true,
      "metrics": {
        "total_configs": 61,
        "valid_configs": 18,
        "unique_configs": 15,
        "avg_response_time": 0.88,
        "success_count": 1,
        "fail_count": 0,
        "overall_score": 76.89,
        "last_success": "2025-04-30T12:41:02.821392"
      }
    },
    {
      "url": "https://t.me/s/v2ray_free_conf",
      "enabled": true,
      "metrics": {
        "total_configs": 19,
        "valid_configs": 16,
        "unique_configs": 16,
        "avg_response_time": 0.35,
        "success_count": 1,
        "fail_count": 0,
        "overall_score": 95.52,
        "last_success": "2025-04-30T12:41:03.288643"
      }
    },
    {
      "url": "https://t.me/s/PrivateVPNs",
      "enabled": true,
      "metrics": {
        "total_configs": 60,
        "valid_configs": 4,
        "unique_configs": 4,
        "avg_response_time": 0,
        "success_count": 0,
        "fail_count": 0,
        "overall_score": 0.0,
        "last_success": null
      }
    },
    {
      "url": "https://t.me/s/freewireguard",
      "enabled": true,
      "metrics": {
        "total_configs": 15,
        "valid_configs": 15,
        "unique_configs": 15,
        "avg_response_time": 0.49,
        "success_count": 1,
        "fail_count": 0,
        "overall_score": 99.26,
        "last_success": "2025-04-30T12:41:16.026560"
      }
    }
  ]
}