{
  "timestamp": "2025-12-16T04:37:11.241222",
  "channels": [
    {
      "url": "https://t.me/s/prrofile_purple",
      "enabled": true,
      "metrics": {
        "total_configs": 32,
        "valid_configs": 18,
        "unique_configs": 18,
        "avg_response_time": 0.63,
        "success_count": 1,
        "fail_count": 0,
        "overall_score": 88.12,
        "last_success": "2025-12-16T04:37:09.697734"
      }
    },
    {
      "url": "https://t.me/s/v2ray_free_conf",
      "enabled": true,
      "metrics": {
        "total_configs": 27,
        "valid_configs": 10,
        "unique_configs": 7,
        "avg_response_time": 0.47,
        "success_count": 1,
        "fail_count": 0,
        "overall_score": 76.06,
        "last_success": "2025-12-16T04:37:10.299379"
      }
    },
    {
      "url": "https://t.me/s/PrivateVPNs",
      "enabled": true,
      "metrics": {
        "total_configs": 16,
        "valid_configs": 15,
        "unique_configs": 15,
        "avg_response_time": 0.44,
        "success_count": 1,
        "fail_count": 0,
        "overall_score": 97.78,
        "last_success": "2025-12-16T04:37:10.773597"
      }
    },
    {
      "url": "https://t.me/s/freewireguard",
      "enabled": true,
      "metrics": {
        "total_configs": 18,
        "valid_configs": 15,
        "unique_configs": 15,
        "avg_response_time": 0.44,
        "success_count": 1,
        "fail_count": 0,
        "overall_score": 95.17,
        "last_success": "2025-12-16T04:37:11.239822"
      }
    }
  ]
}