{
  "timestamp": "2025-12-11T18:34:09.179741",
  "channels": [
    {
      "url": "https://t.me/s/prrofile_purple",
      "enabled": true,
      "metrics": {
        "total_configs": 24,
        "valid_configs": 14,
        "unique_configs": 13,
        "avg_response_time": 0.81,
        "success_count": 1,
        "fail_count": 0,
        "overall_score": 86.58,
        "last_success": "2025-12-11T18:34:07.128540"
      }
    },
    {
      "url": "https://t.me/s/v2ray_free_conf",
      "enabled": true,
      "metrics": {
        "total_configs": 32,
        "valid_configs": 20,
        "unique_configs": 20,
        "avg_response_time": 0.65,
        "success_count": 1,
        "fail_count": 0,
        "overall_score": 89.65,
        "last_success": "2025-12-11T18:34:07.846303"
      }
    },
    {
      "url": "https://t.me/s/PrivateVPNs",
      "enabled": true,
      "metrics": {
        "total_configs": 16,
        "valid_configs": 9,
        "unique_configs": 9,
        "avg_response_time": 0.62,
        "success_count": 1,
        "fail_count": 0,
        "overall_score": 88.13,
        "last_success": "2025-12-11T18:34:08.501515"
      }
    },
    {
      "url": "https://t.me/s/freewireguard",
      "enabled": true,
      "metrics": {
        "total_configs": 19,
        "valid_configs": 15,
        "unique_configs": 15,
        "avg_response_time": 0.65,
        "success_count": 1,
        "fail_count": 0,
        "overall_score": 93.76,
        "last_success": "2025-12-11T18:34:09.177958"
      }
    }
  ]
}