{
  "timestamp": "2025-01-13T05:35:14.511510",
  "channels": [
    {
      "url": "https://t.me/s/prrofile_purple",
      "enabled": true,
      "metrics": {
        "total_configs": 118,
        "valid_configs": 20,
        "unique_configs": 20,
        "avg_response_time": 0.74,
        "success_count": 1,
        "fail_count": 0,
        "overall_score": 78.13,
        "last_success": "2025-01-13T05:35:12.770707"
      }
    },
    {
      "url": "https://t.me/s/v2ray_free_conf",
      "enabled": true,
      "metrics": {
        "total_configs": 39,
        "valid_configs": 17,
        "unique_configs": 17,
        "avg_response_time": 0.44,
        "success_count": 1,
        "fail_count": 0,
        "overall_score": 85.23,
        "last_success": "2025-01-13T05:35:13.289469"
      }
    },
    {
      "url": "https://t.me/s/PrivateVPNs",
      "enabled": true,
      "metrics": {
        "total_configs": 18,
        "valid_configs": 7,
        "unique_configs": 7,
        "avg_response_time": 0.66,
        "success_count": 1,
        "fail_count": 0,
        "overall_score": 83.73,
        "last_success": "2025-01-13T05:35:13.990375"
      }
    },
    {
      "url": "https://t.me/s/freewireguard",
      "enabled": true,
      "metrics": {
        "total_configs": 18,
        "valid_configs": 15,
        "unique_configs": 15,
        "avg_response_time": 0.48,
        "success_count": 1,
        "fail_count": 0,
        "overall_score": 95.11,
        "last_success": "2025-01-13T05:35:14.509650"
      }
    }
  ]
}