{
  "timestamp": "2025-09-19T22:18:12.690259",
  "channels": [
    {
      "url": "https://t.me/s/prrofile_purple",
      "enabled": true,
      "metrics": {
        "total_configs": 23,
        "valid_configs": 11,
        "unique_configs": 11,
        "avg_response_time": 0.85,
        "success_count": 1,
        "fail_count": 0,
        "overall_score": 85.68,
        "last_success": "2025-09-19T22:18:11.028121"
      }
    },
    {
      "url": "https://t.me/s/v2ray_free_conf",
      "enabled": true,
      "metrics": {
        "total_configs": 20,
        "valid_configs": 12,
        "unique_configs": 12,
        "avg_response_time": 0.49,
        "success_count": 1,
        "fail_count": 0,
        "overall_score": 89.26,
        "last_success": "2025-09-19T22:18:11.574726"
      }
    },
    {
      "url": "https://t.me/s/PrivateVPNs",
      "enabled": true,
      "metrics": {
        "total_configs": 16,
        "valid_configs": 15,
        "unique_configs": 15,
        "avg_response_time": 0.48,
        "success_count": 1,
        "fail_count": 0,
        "overall_score": 97.71,
        "last_success": "2025-09-19T22:18:12.094982"
      }
    },
    {
      "url": "https://t.me/s/freewireguard",
      "enabled": true,
      "metrics": {
        "total_configs": 16,
        "valid_configs": 15,
        "unique_configs": 15,
        "avg_response_time": 0.57,
        "success_count": 1,
        "fail_count": 0,
        "overall_score": 97.59,
        "last_success": "2025-09-19T22:18:12.688537"
      }
    }
  ]
}