{
  "timestamp": "2025-06-30T10:24:52.907795",
  "channels": [
    {
      "url": "https://t.me/s/prrofile_purple",
      "enabled": true,
      "metrics": {
        "total_configs": 59,
        "valid_configs": 24,
        "unique_configs": 22,
        "avg_response_time": 0.46,
        "success_count": 1,
        "fail_count": 0,
        "overall_score": 82.39,
        "last_success": "2025-06-30T10:24:51.669046"
      }
    },
    {
      "url": "https://t.me/s/v2ray_free_conf",
      "enabled": true,
      "metrics": {
        "total_configs": 20,
        "valid_configs": 14,
        "unique_configs": 14,
        "avg_response_time": 0.41,
        "success_count": 1,
        "fail_count": 0,
        "overall_score": 91.88,
        "last_success": "2025-06-30T10:24:52.168891"
      }
    },
    {
      "url": "https://t.me/s/PrivateVPNs",
      "enabled": true,
      "metrics": {
        "total_configs": 20,
        "valid_configs": 7,
        "unique_configs": 7,
        "avg_response_time": 0.33,
        "success_count": 1,
        "fail_count": 0,
        "overall_score": 83.26,
        "last_success": "2025-06-30T10:24:52.526979"
      }
    },
    {
      "url": "https://t.me/s/freewireguard",
      "enabled": true,
      "metrics": {
        "total_configs": 14,
        "valid_configs": 14,
        "unique_configs": 14,
        "avg_response_time": 0.34,
        "success_count": 1,
        "fail_count": 0,
        "overall_score": 99.48,
        "last_success": "2025-06-30T10:24:52.905974"
      }
    }
  ]
}